korodata/__init__.py
korodata/korodata.py
korodata-2.1.0.dist-info/AUTHORS.rst
korodata-2.1.0.dist-info/LICENSE
korodata-2.1.0.dist-info/METADATA
korodata-2.1.0.dist-info/WHEEL
korodata-2.1.0.dist-info/top_level.txt
korodata-2.1.0.dist-info/RECORD
